theama/__init__.py
theama/feature_encoding/__init__.py
theama/feature_encoding/bow.py
theama/feature_encoding/vlad.py
theama/feature_encoding/tests/__init__.py
theama/feature_encoding/tests/test_bow.py
theama/feature_encoding/tests/test_vlad.py
theama-0.0.7.dist-info/LICENSE
theama-0.0.7.dist-info/METADATA
theama-0.0.7.dist-info/WHEEL
theama-0.0.7.dist-info/top_level.txt
theama-0.0.7.dist-info/RECORD
